signalstickers_client/__init__.py
signalstickers_client/errors.py
signalstickers_client/stickersclient.py
signalstickers_client/urls.py
signalstickers_client/classes/Stickers_pb2.py
signalstickers_client/classes/__init__.py
signalstickers_client/classes/downloader.py
signalstickers_client/classes/signalcrypto.py
signalstickers_client/classes/uploader.py
signalstickers_client/models/__init__.py
signalstickers_client/models/local_sticker_pack.py
signalstickers_client/models/sticker.py
signalstickers_client/models/sticker_pack.py
signalstickers_client/utils/__init__.py
signalstickers_client/utils/ca/__init__.py
signalstickers_client/utils/ca/ca.py
signalstickers_client/utils/ca/cacert.pem
signalstickers_client-3.3.0.dist-info/LICENSE
signalstickers_client-3.3.0.dist-info/METADATA
signalstickers_client-3.3.0.dist-info/WHEEL
signalstickers_client-3.3.0.dist-info/top_level.txt
signalstickers_client-3.3.0.dist-info/RECORD
